{
    "sourceName": "Premium OTT IPTV",
    "iconUrl": "",
    "author": {
        "name": "Sora Module",
        "icon": "https://cdn-icons-png.flaticon.com/512/3039/3039393.png"
    },
    "version": "1.0.0",
    "language": "Multi-language",
    "streamType": "MP4",
    "quality": "4K - 1080p - 720p - 480p",
    "baseUrl": "http://premium-ott.com:8080",
    "searchBaseUrl": "http://premium-ott.com:8080/player_api.php",
    "scriptUrl": "https://raw.githubusercontent.com/TheSamurai4861/sora-module/refs/heads/main/prod/premium-ott/premium-ott.js",
    "streamAsyncJS": true,
    "type": "shows/movies/anime"
}